Verilog-Sequential/d_latch.v
module d_latch(d,e,q,qn);
    input  d,e;
    output reg q;
    output qn;
always @(*) 
begin
        if(e)
            q=d;
        else
            q=q;
    
end
assign qn=~q;
endmodule

Verilog-Sequential/d_latch_tb.v
module d_latch_tb;
    reg e,d;
    wire q,qn;
d_latch uut(.e(e),.d(d),.q(q),.qn(qn));
initial begin
        $dumpfile("d_latch.vcd");
        $dumpvars(0,d_latch_tb);
        $monitor("Time=%0t|e=%b|d=%b|q=%b|qn=%b",$time,e,d,q,qn);

        e=0;d=0;#10;
        e=1;d=0;#10;
        e=1;d=1;#10;
        e=0;d=0;#10;
        e=0;d=1;#10;
        e=1;d=1;#10;
        e=1;d=0;#10;
        e=0;d=1;#10;
        $finish;
end
endmodule

Verilog-Sequential/d_latch.vcd
$date
	Sun Aug 02 16:28:20 2026
$end
$version
	Icarus Verilog
$end
$timescale
	1s
$end
$scope module d_latch_tb $end
$var wire 1 ! qn $end
$var wire 1 " q $end
$var reg 1 # d $end
$var reg 1 $ e $end
$scope module uut $end
$var wire 1 # d $end
$var wire 1 $ e $end
$var wire 1 ! qn $end
$var reg 1 " q $end
$upscope $end
$upscope $end
$enddefinitions $end
#0
$dumpvars
0$
0#
x"
x!
$end
#10
1!
0"
1$
#20
0!
1"
1#
#30
0#
0$
#40
1#
#50
1$
#60
1!
0"
0#
#70
1#
0$
