Verilog-Sequential/reg_4bit.v
module reg_4bit(clk,d,q);
    input clk;
    input [3:0]d;
    output reg [3:0]q;
always @(posedge clk) 
    begin
        q <= d;
end
endmodule

Verilog-Sequential/reg_4bit_tb.v
module reg_4bit_tb;
    reg [3:0]d;
    reg clk;
    wire [3:0]q;
reg_4bit uut(.clk(clk),.d(d),.q(q));
initial begin
    clk = 0;
    forever #5 clk = ~clk;

end
initial begin
        $dumpfile("reg_4bit.vcd");
        $dumpvars(0,reg_4bit_tb);
        $monitor("Time=%0t|clk=%b|d=%b|q=%b",$time,clk,d,q);
        d=4'b1000;#10;
        d=4'b1101;#10;
        d=4'b1001;#10;
        d=4'b1101;#10;
        $finish;
end
endmodule

Verilog-Sequential/reg_4bit.vcd
$date
	Sun Aug 02 21:36:03 2026
$end
$version
	Icarus Verilog
$end
$timescale
	1s
$end
$scope module reg_4bit_tb $end
$var wire 4 ! q [3:0] $end
$var reg 1 " clk $end
$var reg 4 # d [3:0] $end
$scope module uut $end
$var wire 1 " clk $end
$var wire 4 $ d [3:0] $end
$var reg 4 % q [3:0] $end
$upscope $end
$upscope $end
$enddefinitions $end
#0
$dumpvars
bx %
b1000 $
b1000 #
0"
bx !
$end
#5
b1000 !
b1000 %
1"
#10
0"
b1101 #
b1101 $
#15
b1101 !
b1101 %
1"
#20
0"
b1001 #
b1001 $
#25
b1001 !
b1001 %
1"
#30
0"
b1101 #
b1101 $
#35
b1101 !
b1101 %
1"
